my_own_package/__init__.py
Tedi_first_package-0.1.0.dist-info/METADATA
Tedi_first_package-0.1.0.dist-info/WHEEL
Tedi_first_package-0.1.0.dist-info/top_level.txt
Tedi_first_package-0.1.0.dist-info/RECORD
