Metadata-Version: 2.1
Name: Tedi-first-package
Version: 0.1.0
Summary: my_first_package
Author: Toader-Gavril Farcasanu
Author-email: farcasanu_t@yahoo.com
